myoperator/apm/__init__.py
myoperator/apm/decorators.py
myoperator/apm/metrics.py
myoperator/apm/middlewares.py
myoperator/apm/tests.py
myoperator/centrallog/__init__.py
myoperator/centrallog/centrallog.py
myoperator/centrallog/defaults.py
myoperator/centrallog/helpers.py
myoperator_py-1.0.1.dist-info/AUTHORS.rst
myoperator_py-1.0.1.dist-info/LICENSE
myoperator_py-1.0.1.dist-info/METADATA
myoperator_py-1.0.1.dist-info/WHEEL
myoperator_py-1.0.1.dist-info/top_level.txt
myoperator_py-1.0.1.dist-info/RECORD
