Metadata-Version: 2.1
Name: myoperator-py
Version: 1.0.1
Summary: CentralLog helps recording the logs by MyOperator standards
Home-page: https://github.com/myoperator/centrallog
Author: MyOperator
Author-email: dev@myoperator.co
License: MIT license
Keywords: centrallog
Platform: UNKNOWN
Classifier: Development Status :: 2 - Pre-Alpha
Classifier: Intended Audience :: Developers
Classifier: License :: OSI Approved :: MIT License
Classifier: Natural Language :: English
Classifier: Programming Language :: Python :: 3
Classifier: Programming Language :: Python :: 3.5
Classifier: Programming Language :: Python :: 3.6
Classifier: Programming Language :: Python :: 3.7
Classifier: Programming Language :: Python :: 3.8
Requires-Python: >=3.5
Requires-Dist: statsd (==3.3.0)
Requires-Dist: Django (>=1.8.0)
